proxy_rotator_toolkit/__init__.py
proxy_rotator_toolkit/custom_exceptions.py
proxy_rotator_toolkit/notification.py
proxy_rotator_toolkit/proxy_rotation.py
proxy_rotator_toolkit-0.0.26.dist-info/METADATA
proxy_rotator_toolkit-0.0.26.dist-info/WHEEL
proxy_rotator_toolkit-0.0.26.dist-info/top_level.txt
proxy_rotator_toolkit-0.0.26.dist-info/RECORD
