Metadata-Version: 2.1
Name: proxy-rotator-toolkit
Version: 0.0.26
Summary: Proxy rotation is a project designed to simplify working with the proxy rotation
Author: Webparsers
Author-email: panenotgeor@gmail.com
Classifier: Programming Language :: Python :: 3
Classifier: License :: OSI Approved :: MIT License
Classifier: Operating System :: OS Independent
Requires-Python: >=3.7
Requires-Dist: apprise==1.9.1
Requires-Dist: curl-cffi>=0.7.4
